uartTR.v
module uartT(input clk,
input reset,
input [8:1]data_in,
input transfer,
output reg transfering,
output reg data_out,
output baud_tick,
output reg[3:0]inte);
reg[1:0]i;
reg baud;
always @(posedge clk)begin
    if(reset)
    begin
        i<=0;
        baud<=0;
    end
    else begin
if(i==2'd3)begin
    baud<=1;
    i<=2'd0;
end
else begin
    i<=i+2'd1;
    baud<=0;
end

end
end
always @(posedge clk or posedge reset) begin
    if(transfer)
transfering<=1;
else begin
    
end
    if(reset)
    begin
     inte<=0;data_out<=1;transfering<=0;
    end
    else if(baud)
    begin
      if(transfering)
      begin 
        if(inte==0&&data_out==1)begin
            data_out<=0;    
            end
        else if(inte<4'd8)
        begin 
            inte=inte+4'd1; 
            data_out=data_in[inte]; 
        
        end
        else 
        begin // 9 is the stop num. 
        data_out<=1; inte<=9;// inte will become 0 again when reset is on so that next new msg will go.
        transfering<=0;
        end
        end
        else begin
            data_out<=1;
        end
    end
    else begin   inte<=inte;end
end
assign baud_tick=baud;
endmodule


//receiver


module uartR(input data_in,
input clk,
input reset,
input baud,
output reg active,
output reg [7:0]data_out,
output reg received,
output baud_tick
);
reg [3:0]i;
reg[1:0]j;
assign baud_tick=baud;

always @(posedge clk)
begin
    if(reset)
    begin
        data_out<=8'd0;
        active<=0;i<=0;
        received<=0;
       
    end
    else begin
        if(baud)begin
        if(data_in==0&&active==0)
        active<=1;
        else if(active)
        begin
            if(i!=8)begin data_out[i]<=data_in;
            i<=i+3'd1;end
            else begin
                if(i==8&&data_in==1)begin
             active<=0; received<=1; i<=i+1; end
             else if(i==8&&data_in==0) begin
                active<=0;received<=0;i<=i+1;end
                else begin 
                    i<=0;
                    active<=0;
                end 
                end
                end 
                else begin
        
        end  
            end
        end
        end
endmodule


//mixi


module mixI(input clk,
    input reset,
    input transfer,
    input [8:1] data_in,
    output dataT,
    output baud1,
    output [7:0] dataR,
    output received);
wire[7:0]x;
wire y;
wire fakebaud;  
assign baud1=fakebaud;
assign dataR=x;
assign dataT=y;
uartT DUT1(
    .clk(clk),
    .reset(reset),
    .data_in(data_in),
    .transfer(transfer),
    .data_out(y),
    .baud_tick(fakebaud)
    );
uartR DUT2(
    .clk(clk),
    .reset(reset),
    .baud(fakebaud),
    .data_in(y),
    .data_out(x),
    .received(received));
endmodule

uarttbTR.v
module testuart;
reg clk, reset,transfer;
reg [8:1]data_in;
wire baud_tick;
wire dataT,received;
wire[7:0]dataR;
mixI DUT1(
      .clk(clk),
      .reset(reset),
      .data_in(data_in),
      .dataT(dataT),
      .dataR(dataR),
      .transfer(transfer),
      .received(received),
      .baud1(baud_tick));
initial begin
    $dumpfile("uartTR.vcd");
    $dumpvars(0,testuart);
    reset=1;clk=0;
    @(posedge clk)
    data_in=8'b10010011;
    @(posedge clk)
    reset=0;transfer=1;
    #250;// to transfer another input , just reset and continue the same process.
    reset=1;transfer=0;
    #5;reset=0;transfer=1;
    data_in=8'b11110011;
    #250;
    $finish;
end
always #2 clk =~clk;
always @(posedge clk)begin
 if(baud_tick)   
    $display("T=%0t ,data=%0b,DATA=%0h",$time,dataT,dataR);
end
endmodule

uartTR.vcd
$date
	Sun Feb 01 15:13:56 2026
$end
$version
	Icarus Verilog
$end
$timescale
	1s
$end
$scope module testuart $end
$var wire 1 ! received $end
$var wire 1 " dataT $end
$var wire 8 # dataR [7:0] $end
$var wire 1 $ baud_tick $end
$var reg 1 % clk $end
$var reg 8 & data_in [8:1] $end
$var reg 1 ' reset $end
$var reg 1 ( transfer $end
$scope module DUT1 $end
$var wire 1 $ baud1 $end
$var wire 1 % clk $end
$var wire 8 ) dataR [7:0] $end
$var wire 1 " dataT $end
$var wire 8 * data_in [8:1] $end
$var wire 1 ' reset $end
$var wire 1 ( transfer $end
$var wire 1 + y $end
$var wire 8 , x [7:0] $end
$var wire 1 ! received $end
$var wire 1 - fakebaud $end
$scope module DUT1 $end
$var wire 1 - baud_tick $end
$var wire 1 % clk $end
$var wire 8 . data_in [8:1] $end
$var wire 1 ' reset $end
$var wire 1 ( transfer $end
$var reg 1 - baud $end
$var reg 1 + data_out $end
$var reg 2 / i [1:0] $end
$var reg 4 0 inte [3:0] $end
$var reg 1 1 transfering $end
$upscope $end
$scope module DUT2 $end
$var wire 1 - baud $end
$var wire 1 2 baud_tick $end
$var wire 1 % clk $end
$var wire 1 + data_in $end
$var wire 1 ' reset $end
$var reg 1 3 active $end
$var reg 8 4 data_out [7:0] $end
$var reg 4 5 i [3:0] $end
$var reg 1 ! received $end
$upscope $end
$upscope $end
$upscope $end
$enddefinitions $end
$comment Show the parameter values. $end
$dumpall
$end
#0
$dumpvars
bx 5
bx 4
x3
x2
01
b0 0
bx /
bx .
x-
bx ,
1+
bx *
bx )
x(
1'
bx &
0%
x$
bx #
1"
x!
$end
#2
02
0$
0-
b0 /
0!
b0 5
03
b0 #
b0 )
b0 ,
b0 4
b10010011 &
b10010011 *
b10010011 .
1%
#4
0%
#6
11
1(
0'
1%
#8
0%
#10
b1 /
1%
#12
0%
#14
b10 /
1%
#16
0%
#18
b11 /
1%
#20
0%
#22
b0 /
12
1$
1-
1%
#24
0%
#26
0"
0+
02
0$
0-
b1 /
1%
#28
0%
#30
b10 /
1%
#32
0%
#34
b11 /
1%
#36
0%
#38
b0 /
12
1$
1-
1%
#40
0%
#42
02
0$
0-
b1 /
13
1"
1+
b1 0
1%
#44
0%
#46
b10 /
1%
#48
0%
#50
b11 /
1%
#52
0%
#54
b0 /
12
1$
1-
1%
#56
0%
#58
02
0$
0-
b1 /
b1 5
b1 #
b1 )
b1 ,
b1 4
b10 0
1%
#60
0%
#62
b10 /
1%
#64
0%
#66
b11 /
1%
#68
0%
#70
b0 /
12
1$
1-
1%
#72
0%
#74
02
0$
0-
b1 /
b10 5
b11 #
b11 )
b11 ,
b11 4
0"
0+
b11 0
1%
#76
0%
#78
b10 /
1%
#80
0%
#82
b11 /
1%
#84
0%
#86
b0 /
12
1$
1-
1%
#88
0%
#90
02
0$
0-
b1 /
b11 5
b100 0
1%
#92
0%
#94
b10 /
1%
#96
0%
#98
b11 /
1%
#100
0%
#102
b0 /
12
1$
1-
1%
#104
0%
#106
02
0$
0-
b1 /
b100 5
1"
1+
b101 0
1%
#108
0%
#110
b10 /
1%
#112
0%
#114
b11 /
1%
#116
0%
#118
b0 /
12
1$
1-
1%
#120
0%
#122
02
0$
0-
b1 /
b101 5
b10011 #
b10011 )
b10011 ,
b10011 4
0"
0+
b110 0
1%
#124
0%
#126
b10 /
1%
#128
0%
#130
b11 /
1%
#132
0%
#134
b0 /
12
1$
1-
1%
#136
0%
#138
02
0$
0-
b1 /
b110 5
b111 0
1%
#140
0%
#142
b10 /
1%
#144
0%
#146
b11 /
1%
#148
0%
#150
b0 /
12
1$
1-
1%
#152
0%
#154
02
0$
0-
b1 /
b111 5
1"
1+
b1000 0
1%
#156
0%
#158
b10 /
1%
#160
0%
#162
b11 /
1%
#164
0%
#166
b0 /
12
1$
1-
1%
#168
0%
#170
01
b1001 0
02
0$
0-
b1 /
b1000 5
b10010011 #
b10010011 )
b10010011 ,
b10010011 4
1%
#172
0%
#174
11
b10 /
1%
#176
0%
#178
b11 /
1%
#180
0%
#182
b0 /
12
1$
1-
1%
#184
0%
#186
01
02
0$
0-
b1 /
b1001 5
1!
03
1%
#188
0%
#190
11
b10 /
1%
#192
0%
#194
b11 /
1%
#196
0%
#198
b0 /
12
1$
1-
1%
#200
0%
#202
01
02
0$
0-
b1 /
1%
#204
0%
#206
11
b10 /
1%
#208
0%
#210
b11 /
1%
#212
0%
#214
b0 /
12
1$
1-
1%
#216
0%
#218
01
02
0$
0-
b1 /
1%
#220
0%
#222
11
b10 /
1%
#224
0%
#226
b11 /
1%
#228
0%
#230
b0 /
12
1$
1-
1%
#232
0%
#234
01
02
0$
0-
b1 /
1%
#236
0%
#238
11
b10 /
1%
#240
0%
#242
b11 /
1%
#244
0%
#246
b0 /
12
1$
1-
1%
#248
0%
#250
01
02
0$
0-
b1 /
1%
#252
0%
#254
11
b10 /
1%
#256
01
b0 0
0%
0(
1'
#258
b0 /
0!
b0 5
b0 #
b0 )
b0 ,
b0 4
1%
#260
0%
#261
b11110011 &
b11110011 *
b11110011 .
1(
0'
#262
11
b1 /
1%
#264
0%
#266
b10 /
1%
#268
0%
#270
b11 /
1%
#272
0%
#274
b0 /
12
1$
1-
1%
#276
0%
#278
0"
0+
02
0$
0-
b1 /
1%
#280
0%
#282
b10 /
1%
#284
0%
#286
b11 /
1%
#288
0%
#290
b0 /
12
1$
1-
1%
#292
0%
#294
13
02
0$
0-
b1 /
1"
1+
b1 0
1%
#296
0%
#298
b10 /
1%
#300
0%
#302
b11 /
1%
#304
0%
#306
b0 /
12
1$
1-
1%
#308
0%
#310
b1 5
b1 #
b1 )
b1 ,
b1 4
02
0$
0-
b1 /
b10 0
1%
#312
0%
#314
b10 /
1%
#316
0%
#318
b11 /
1%
#320
0%
#322
b0 /
12
1$
1-
1%
#324
0%
#326
b10 5
b11 #
b11 )
b11 ,
b11 4
02
0$
0-
b1 /
0"
0+
b11 0
1%
#328
0%
#330
b10 /
1%
#332
0%
#334
b11 /
1%
#336
0%
#338
b0 /
12
1$
1-
1%
#340
0%
#342
b11 5
02
0$
0-
b1 /
b100 0
1%
#344
0%
#346
b10 /
1%
#348
0%
#350
b11 /
1%
#352
0%
#354
b0 /
12
1$
1-
1%
#356
0%
#358
b100 5
02
0$
0-
b1 /
1"
1+
b101 0
1%
#360
0%
#362
b10 /
1%
#364
0%
#366
b11 /
1%
#368
0%
#370
b0 /
12
1$
1-
1%
#372
0%
#374
b101 5
b10011 #
b10011 )
b10011 ,
b10011 4
02
0$
0-
b1 /
b110 0
1%
#376
0%
#378
b10 /
1%
#380
0%
#382
b11 /
1%
#384
0%
#386
b0 /
12
1$
1-
1%
#388
0%
#390
b110 5
b110011 #
b110011 )
b110011 ,
b110011 4
02
0$
0-
b1 /
b111 0
1%
#392
0%
#394
b10 /
1%
#396
0%
#398
b11 /
1%
#400
0%
#402
b0 /
12
1$
1-
1%
#404
0%
#406
b111 5
b1110011 #
b1110011 )
b1110011 ,
b1110011 4
02
0$
0-
b1 /
b1000 0
1%
#408
0%
#410
b10 /
1%
#412
0%
#414
b11 /
1%
#416
0%
#418
b0 /
12
1$
1-
1%
#420
0%
#422
01
b1001 0
b1000 5
b11110011 #
b11110011 )
b11110011 ,
b11110011 4
02
0$
0-
b1 /
1%
#424
0%
#426
11
b10 /
1%
#428
0%
#430
b11 /
1%
#432
0%
#434
b0 /
12
1$
1-
1%
#436
0%
#438
01
b1001 5
1!
03
02
0$
0-
b1 /
1%
#440
0%
#442
11
b10 /
1%
#444
0%
#446
b11 /
1%
#448
0%
#450
b0 /
12
1$
1-
1%
#452
0%
#454
01
02
0$
0-
b1 /
1%
#456
0%
#458
11
b10 /
1%
#460
0%
#462
b11 /
1%
#464
0%
#466
b0 /
12
1$
1-
1%
#468
0%
#470
01
02
0$
0-
b1 /
1%
#472
0%
#474
11
b10 /
1%
#476
0%
#478
b11 /
1%
#480
0%
#482
b0 /
12
1$
1-
1%
#484
0%
#486
01
02
0$
0-
b1 /
1%
#488
0%
#490
11
b10 /
1%
#492
0%
#494
b11 /
1%
#496
0%
#498
b0 /
12
1$
1-
1%
#500
0%
#502
01
02
0$
0-
b1 /
1%
#504
0%
#506
11
b10 /
1%
#508
0%
#510
b11 /
1%
